sfftkrw/__init__.py
sfftkrw/conf.py
sfftkrw/sffrw.py
sfftkrw/core/__init__.py
sfftkrw/core/parser.py
sfftkrw/core/print_tools.py
sfftkrw/core/utils.py
sfftkrw/schema/__init__.py
sfftkrw/schema/adapter_v0_7_0_dev0.py
sfftkrw/schema/adapter_v0_8_0_dev1.py
sfftkrw/schema/base.py
sfftkrw/schema/emdb_sff.py
sfftkrw/schema/v0_5_8.py
sfftkrw/schema/v0_6_0_a2.py
sfftkrw/schema/v0_6_0_a3.py
sfftkrw/schema/v0_6_0_a4.py
sfftkrw/schema/v0_7_0_dev0.py
sfftkrw/schema/v0_8_0_dev0.py
sfftkrw/schema/v0_8_0_dev1.py
sfftkrw/test_data/__init__.py
sfftkrw/unittests/__init__.py
sfftkrw/unittests/test_adapter_v0_7_0_dev0.py
sfftkrw/unittests/test_adapter_v0_8_0_dev1.py
sfftkrw/unittests/test_base.py
sfftkrw/unittests/test_core.py
sfftkrw/unittests/test_main.py
sfftk_rw-0.8.1.dist-info/LICENSE
sfftk_rw-0.8.1.dist-info/METADATA
sfftk_rw-0.8.1.dist-info/WHEEL
sfftk_rw-0.8.1.dist-info/entry_points.txt
sfftk_rw-0.8.1.dist-info/top_level.txt
sfftk_rw-0.8.1.dist-info/RECORD
