Metadata-Version: 2.1
Name: sfftk-rw
Version: 0.8.1
Summary: Toolkit for reading and writing EMDB-SFF files
Home-page: http://sfftk-rw.readthedocs.io/en/latest/index.html
Author: Paul K. Korir, PhD
Author-email: pkorir@ebi.ac.uk, paul.korir@gmail.com
License: Apache License 2.0
Keywords: EMDB-SFF,SFF,segmentation
Classifier: Development Status :: 4 - Beta
Classifier: Environment :: Console
Classifier: Intended Audience :: Developers
Classifier: Intended Audience :: Science/Research
Classifier: License :: OSI Approved :: Apache Software License
Classifier: Operating System :: OS Independent
Classifier: Programming Language :: Python :: 3
Classifier: Programming Language :: Python :: 3.6
Classifier: Programming Language :: Python :: 3.7
Classifier: Programming Language :: Python :: 3.8
Classifier: Programming Language :: Python :: 3.9
Classifier: Programming Language :: Python :: 3.10
Classifier: Programming Language :: Python :: 3.11
Classifier: Topic :: Software Development :: Libraries :: Python Modules
Classifier: Topic :: Terminals
Classifier: Topic :: Text Processing
Classifier: Topic :: Text Processing :: Markup
Classifier: Topic :: Utilities
Requires-Python: >=3.6
License-File: LICENSE
Requires-Dist: six
Requires-Dist: numpy
Requires-Dist: lxml
Requires-Dist: h5py
Requires-Dist: RandomWords
